alarmdecoder/__init__.py
alarmdecoder/decoder.py
alarmdecoder/panels.py
alarmdecoder/states.py
alarmdecoder/util.py
alarmdecoder/zonetracking.py
alarmdecoder/devices/__init__.py
alarmdecoder/devices/base_device.py
alarmdecoder/devices/serial_device.py
alarmdecoder/devices/socket_device.py
alarmdecoder/devices/usb_device.py
alarmdecoder/event/__init__.py
alarmdecoder/event/event.py
alarmdecoder/messages/__init__.py
alarmdecoder/messages/aui_message.py
alarmdecoder/messages/base_message.py
alarmdecoder/messages/expander_message.py
alarmdecoder/messages/panel_message.py
alarmdecoder/messages/rf_message.py
alarmdecoder/messages/lrr/__init__.py
alarmdecoder/messages/lrr/events.py
alarmdecoder/messages/lrr/message.py
alarmdecoder/messages/lrr/system.py
alarmdecoder-1.13.14.data/scripts/ad2-firmwareupload
alarmdecoder-1.13.14.data/scripts/ad2-sslterm
alarmdecoder-1.13.14.dist-info/licenses/LICENSE
alarmdecoder-1.13.14.dist-info/METADATA
alarmdecoder-1.13.14.dist-info/WHEEL
alarmdecoder-1.13.14.dist-info/top_level.txt
alarmdecoder-1.13.14.dist-info/RECORD
