Metadata-Version: 2.4
Name: alarmdecoder
Version: 1.13.14
Summary: Python interface for the AlarmDecoder (AD2) family of alarm devices which includes the AD2USB, AD2SERIAL and AD2PI.
Home-page: http://github.com/nutechsoftware/alarmdecoder
Author: Nu Tech Software Solutions, Inc.
Author-email: general@support.nutech.com
License: MIT
Keywords: alarmdecoder alarm decoder ad2 ad2usb ad2serial ad2pi security ademco dsc nutech
Classifier: Development Status :: 5 - Production/Stable
Classifier: License :: OSI Approved :: MIT License
Classifier: Programming Language :: Python :: 2.7
Classifier: Programming Language :: Python :: 3.4
Classifier: Topic :: Software Development :: Libraries :: Python Modules
Classifier: Topic :: Communications
Classifier: Topic :: Home Automation
Classifier: Topic :: Security
License-File: LICENSE
Requires-Dist: pyserial>=2.7
Dynamic: author
Dynamic: author-email
Dynamic: classifier
Dynamic: description
Dynamic: home-page
Dynamic: keywords
Dynamic: license
Dynamic: license-file
Dynamic: requires-dist
Dynamic: summary
